Workbook

Sheet Entradas
A1: Simulador de Salário Líquido Anual em Portugal
A3: Campo | B3: Valor
A4: Salário bruto mensal (€) | B4: 3000
A5: Número de salários | B5: 14
A6: Estado civil | B6: Casado 2 titulares
A7: N.º dependentes | B7: 2
A8: Região fiscal | B8: Continente
A9: Subsídio alimentação mensal (€) | B9: 200
A10: Meses de subsídio alimentação | B10: 11
A11: Subsídio alimentação isento mensal (€) | B11: 600
A12: IRS Jovem | B12: Não
A13: Idade | B13: 42
A14: Ano IRS Jovem | B14: 0
A16: Observação
A17: Este ficheiro faz uma estimativa anual com base nos escalões de IRS 2026 e Segurança Social do trabalhador.
A18: A retenção mensal na fonte pode diferir do IRS final anual.
A19: Para decisão final, validar com contabilista/AT, sobretudo em casos com deduções, regimes especiais ou rendimentos adicionais.
A20: Regiões Autónomas, deficiência fiscal, pensões, recibos verdes e regimes especiais não estão totalmente modelados.
A21: Atualize a aba Parâmetros/Escalões quando houver nova legislação.
A23: Sheet | B23: Freelancer_vs_Contrato
A24: Objetivo | B24: Comparar salário líquido anual por contrato com taxa dia de freelancer

Sheet Simulador
A1: Simulador - Salário Líquido Anual
A3: Indicador | B3: Fórmula/Valor | C3: Nota | E3: Resumo rápido
A4: Salário bruto anual | B4: =Entradas!B4*Entradas!B5 -> 42000 | C4: Salário bruto mensal × nº salários | E4: Bruto anual | F4: =B4 -> 42000
A5: Subsídio alimentação anual | B5: =Entradas!B9*Entradas!B10 -> 2200 | C5: Valor mensal × meses | E5: SS anual | F5: =B9 -> 4620
A6: Parte isenta subsídio alimentação | B6: =MIN(Entradas!B9,Entradas!B11)*Entradas!B10 -> 2200 | C6: Até ao limite mensal indicado | E6: IRS anual | F6: =B16 -> 8835.773
A7: Parte tributável subsídio alimentação | B7: =MAX(0,B5-B6) -> 0 | C7: Excesso integrado na base | E7: Líquido anual | F7: =B17 -> 30744.227
A8: Rendimento bruto tributável | B8: =B4+B7+Parâmetros!B11 -> 42000 | C8: Salário + subsídio alimentação tributável + outros rendimentos | E8: Líquido médio/mês | F8: =B18 -> 2196.0162
A9: Segurança Social anual | B9: =B4*Parâmetros!B4 -> 4620 | C9: 11% sobre salário bruto | E9: Taxa efetiva | F9: =B19 -> 0.30442925
A10: Dedução específica considerada | B10: =MAX(Parâmetros!B5,B9) -> 4620 | C10: Maior entre dedução específica e SS anual
A11: Rendimento coletável antes IRS Jovem | B11: =MAX(0,B8-B10) -> 37380 | C11: Base para aplicar escalões
A12: Isenção IRS Jovem estimada | B12: =IF(Entradas!B12="Sim",MIN(B11,VLOOKUP(Entradas!B14,Parâmetros!E4:G10,2,FALSE)*VLOOKUP(Entradas!B14,Parâmetros!E4:G10,3,FALSE)),0) -> 0 | C12: Parametrizada e opcional
A13: Rendimento coletável para IRS | B13: =MAX(0,B11-B12) -> 37380 | C13: Após eventual isenção
A14: IRS anual bruto estimado | B14: =MAX(0,MIN(B13,Escalões_IRS_2026!C4)-Escalões_IRS_2026!B4)*Escalões_IRS_2026!D4+MAX(0,MIN(B13,Escalões_IRS_2026!C5)-Escalões_IRS_2026!B5)*Escalões_IRS_2026!D5+MAX(0,MIN(B13,Escalões_IRS_2026!C6)-Escalões_IRS_2026!B6)*Escalões_IRS_2026!D6+MAX(0,MIN(B13,Escalões_IRS_2026!C7)-Escalões_IRS_2026!B7)*Escalões_IRS_2026!D7+MAX(0,MIN(B13,Escalões_IRS_2026!C8)-Escalões_IRS_2026!B8)*Escalões_IRS_2026!D8+MAX(0,MIN(B13,Escalões_IRS_2026!C9)-Escalões_IRS_2026!B9)*Escalões_IRS_2026!D9+MAX(0,MIN(B13,Escalões_IRS_2026!C10)-Escalões_IRS_2026!B10)*Escalões_IRS_2026!D10+MAX(0,MIN(B13,Escalões_IRS_2026!C11)-Escalões_IRS_2026!B11)*Escalões_IRS_2026!D11+MAX(0,MIN(B13,Escalões_IRS_2026!C12)-Escalões_IRS_2026!B12)*Escalões_IRS_2026!D12 -> 8835.773 | C14: Cálculo progressivo
A15: Deduções à coleta | B15: =Parâmetros!B9+Parâmetros!B10 -> 0 | C15: Campos livres em Parâmetros
A16: IRS anual líquido estimado | B16: =MAX(0,B14-B15) -> 8835.773 | C16: Mínimo zero
A17: Salário líquido anual estimado | B17: =B4+B5-B9-B16 -> 30744.227 | C17: Bruto + subsídio alimentação - SS - IRS
A18: Líquido mensal médio em 14 salários | B18: =B17/Entradas!B5 -> 2196.0162 | C18: Líquido anual / nº salários
A19: Taxa efetiva descontos | B19: =IFERROR((B9+B16)/(B4+B5),0) -> 0.30442925 | C19: (SS + IRS) / total recebido
A25: Idealização: Felipe Manso - Consultor LO (MM/SD) 🔗 LinkedIn: https://www.linkedin.com/in/sapfelipemanso

Sheet Escalões_IRS_2026
A1: Escalões de IRS 2026 - Continente (estimativo)
A3: Escalão | B3: Limite inferior (€) | C3: Limite superior (€) | D3: Taxa marginal | E3: Imposto máximo no escalão
A4: 1 | B4: 0 | C4: 8342 | D4: 0.125 | E4: =MAX(0,C4-B4)*D4 -> 1042.75
A5: 2 | B5: 8342 | C5: 12587 | D5: 0.157 | E5: =MAX(0,C5-B5)*D5 -> 666.465
A6: 3 | B6: 12587 | C6: 17838 | D6: 0.212 | E6: =MAX(0,C6-B6)*D6 -> 1113.212
A7: 4 | B7: 17838 | C7: 23089 | D7: 0.241 | E7: =MAX(0,C7-B7)*D7 -> 1265.491
A8: 5 | B8: 23089 | C8: 29397 | D8: 0.311 | E8: =MAX(0,C8-B8)*D8 -> 1961.788
A9: 6 | B9: 29397 | C9: 43090 | D9: 0.349 | E9: =MAX(0,C9-B9)*D9 -> 4778.857
A10: 7 | B10: 43090 | C10: 46566 | D10: 0.431 | E10: =MAX(0,C10-B10)*D10 -> 1498.156
A11: 8 | B11: 46566 | C11: 86634 | D11: 0.446 | E11: =MAX(0,C11-B11)*D11 -> 17870.328
A12: 9 | B12: 86634 | C12: 999999999 | D12: 0.48 | E12: =MAX(0,C12-B12)*D12 -> 4.7995842e+08

Sheet Parâmetros
A1: Parâmetros do Modelo
A3: Parâmetro | B3: Valor | C3: Nota | E3: IRS Jovem - ano | F3: % isenção | G3: Limite anual (€) | H3: Nota
A4: Segurança Social trabalhador | B4: 0.11 | C4: Regime geral por conta de outrem | E4: 1 | F4: 1 | G4: 28737.5 | H4: Parametrizável
A5: Dedução específica Categoria A | B5: 4104 | C5: Usada se superior à contribuição SS anual | E5: 2 | F5: 0.75 | G5: 28737.5 | H5: Parametrizável
A6: Limite subsídio refeição cartão/dia | B6: 10.2 | C6: Estimativa: 22 dias úteis/mês | E6: 3 | F6: 0.5 | G6: 28737.5 | H6: Parametrizável
A7: Dias úteis médios/mês | B7: 22 | C7: Para cálculo do limite isento mensal | E7: 4 | F7: 0.5 | G7: 28737.5 | H7: Parametrizável
A8: Taxa autónoma excesso subsídio refeição | B8: 0 | C8: Modelo trata excesso como rendimento tributável | E8: 5 | F8: 0.25 | G8: 28737.5 | H8: Parametrizável
A9: Deduções à coleta pessoais | B9: 0 | C9: Campo livre para o utilizador | E9: 0 | F9: 0 | G9: 0 | H9: Sem aplicação
A10: Outras deduções à coleta | B10: 0 | C10: Campo livre para o utilizador
A11: Outros rendimentos tributáveis anuais | B11: 0 | C11: Campo livre para o utilizador
A12: Ano fiscal | B12: 2026

Sheet Comparador Contrato
A1: Comparador de Cenários
A3: Cenário | B3: Bruto mensal | C3: N.º salários | D3: Bruto anual | E3: SS anual | F3: IRS estimado | G3: Líquido anual | H3: Líquido médio/mês
A4: Cenário 1 | B4: 2000 | C4: 14 | D4: =B4*C4 -> 28000 | E4: =D4*Parâmetros!$B$4 -> 3080 | F4: =MAX(0,(MAX(0,MIN(MAX(0,D4-MAX(Parâmetros!$B$5,E4)),Escalões_IRS_2026!$C$4)-Escalões_IRS_2026!$B$4)*Escalões_IRS_2026!$D$4+MAX(0,MIN(MAX(0,D4-MAX(Parâmetros!$B$5,E4)),Escalões_IRS_2026!$C$5)-Escalões_IRS_2026!$B$5)*Escalões_IRS_2026!$D$5+MAX(0,MIN(MAX(0,D4-MAX(Parâmetros!$B$5,E4)),Escalões_IRS_2026!$C$6)-Escalões_IRS_2026!$B$6)*Escalões_IRS_2026!$D$6+MAX(0,MIN(MAX(0,D4-MAX(Parâmetros!$B$5,E4)),Escalões_IRS_2026!$C$7)-Escalões_IRS_2026!$B$7)*Escalões_IRS_2026!$D$7+MAX(0,MIN(MAX(0,D4-MAX(Parâmetros!$B$5,E4)),Escalões_IRS_2026!$C$8)-Escalões_IRS_2026!$B$8)*Escalões_IRS_2026!$D$8+MAX(0,MIN(MAX(0,D4-MAX(Parâmetros!$B$5,E4)),Escalões_IRS_2026!$C$9)-Escalões_IRS_2026!$B$9)*Escalões_IRS_2026!$D$9+MAX(0,MIN(MAX(0,D4-MAX(Parâmetros!$B$5,E4)),Escalões_IRS_2026!$C$10)-Escalões_IRS_2026!$B$10)*Escalões_IRS_2026!$D$10+MAX(0,MIN(MAX(0,D4-MAX(Parâmetros!$B$5,E4)),Escalões_IRS_2026!$C$11)-Escalões_IRS_2026!$B$11)*Escalões_IRS_2026!$D$11+MAX(0,MIN(MAX(0,D4-MAX(Parâmetros!$B$5,E4)),Escalões_IRS_2026!$C$12)-Escalões_IRS_2026!$B$12)*Escalões_IRS_2026!$D$12)-Parâmetros!$B$9-Parâmetros!$B$10) -> 4338.895 | G4: =D4-E4-F4 -> 20581.105 | H4: =G4/C4 -> 1470.0789
A5: Cenário 2 | B5: 3000 | C5: 14 | D5: =B5*C5 -> 42000 | E5: =D5*Parâmetros!$B$4 -> 4620 | F5: =MAX(0,(MAX(0,MIN(MAX(0,D5-MAX(Parâmetros!$B$5,E5)),Escalões_IRS_2026!$C$4)-Escalões_IRS_2026!$B$4)*Escalões_IRS_2026!$D$4+MAX(0,MIN(MAX(0,D5-MAX(Parâmetros!$B$5,E5)),Escalões_IRS_2026!$C$5)-Escalões_IRS_2026!$B$5)*Escalões_IRS_2026!$D$5+MAX(0,MIN(MAX(0,D5-MAX(Parâmetros!$B$5,E5)),Escalões_IRS_2026!$C$6)-Escalões_IRS_2026!$B$6)*Escalões_IRS_2026!$D$6+MAX(0,MIN(MAX(0,D5-MAX(Parâmetros!$B$5,E5)),Escalões_IRS_2026!$C$7)-Escalões_IRS_2026!$B$7)*Escalões_IRS_2026!$D$7+MAX(0,MIN(MAX(0,D5-MAX(Parâmetros!$B$5,E5)),Escalões_IRS_2026!$C$8)-Escalões_IRS_2026!$B$8)*Escalões_IRS_2026!$D$8+MAX(0,MIN(MAX(0,D5-MAX(Parâmetros!$B$5,E5)),Escalões_IRS_2026!$C$9)-Escalões_IRS_2026!$B$9)*Escalões_IRS_2026!$D$9+MAX(0,MIN(MAX(0,D5-MAX(Parâmetros!$B$5,E5)),Escalões_IRS_2026!$C$10)-Escalões_IRS_2026!$B$10)*Escalões_IRS_2026!$D$10+MAX(0,MIN(MAX(0,D5-MAX(Parâmetros!$B$5,E5)),Escalões_IRS_2026!$C$11)-Escalões_IRS_2026!$B$11)*Escalões_IRS_2026!$D$11+MAX(0,MIN(MAX(0,D5-MAX(Parâmetros!$B$5,E5)),Escalões_IRS_2026!$C$12)-Escalões_IRS_2026!$B$12)*Escalões_IRS_2026!$D$12)-Parâmetros!$B$9-Parâmetros!$B$10) -> 8835.773 | G5: =D5-E5-F5 -> 28544.227 | H5: =G5/C5 -> 2038.8734
A6: Cenário 3 | B6: 4000 | C6: 14 | D6: =B6*C6 -> 56000 | E6: =D6*Parâmetros!$B$4 -> 6160 | F6: =MAX(0,(MAX(0,MIN(MAX(0,D6-MAX(Parâmetros!$B$5,E6)),Escalões_IRS_2026!$C$4)-Escalões_IRS_2026!$B$4)*Escalões_IRS_2026!$D$4+MAX(0,MIN(MAX(0,D6-MAX(Parâmetros!$B$5,E6)),Escalões_IRS_2026!$C$5)-Escalões_IRS_2026!$B$5)*Escalões_IRS_2026!$D$5+MAX(0,MIN(MAX(0,D6-MAX(Parâmetros!$B$5,E6)),Escalões_IRS_2026!$C$6)-Escalões_IRS_2026!$B$6)*Escalões_IRS_2026!$D$6+MAX(0,MIN(MAX(0,D6-MAX(Parâmetros!$B$5,E6)),Escalões_IRS_2026!$C$7)-Escalões_IRS_2026!$B$7)*Escalões_IRS_2026!$D$7+MAX(0,MIN(MAX(0,D6-MAX(Parâmetros!$B$5,E6)),Escalões_IRS_2026!$C$8)-Escalões_IRS_2026!$B$8)*Escalões_IRS_2026!$D$8+MAX(0,MIN(MAX(0,D6-MAX(Parâmetros!$B$5,E6)),Escalões_IRS_2026!$C$9)-Escalões_IRS_2026!$B$9)*Escalões_IRS_2026!$D$9+MAX(0,MIN(MAX(0,D6-MAX(Parâmetros!$B$5,E6)),Escalões_IRS_2026!$C$10)-Escalões_IRS_2026!$B$10)*Escalões_IRS_2026!$D$10+MAX(0,MIN(MAX(0,D6-MAX(Parâmetros!$B$5,E6)),Escalões_IRS_2026!$C$11)-Escalões_IRS_2026!$B$11)*Escalões_IRS_2026!$D$11+MAX(0,MIN(MAX(0,D6-MAX(Parâmetros!$B$5,E6)),Escalões_IRS_2026!$C$12)-Escalões_IRS_2026!$B$12)*Escalões_IRS_2026!$D$12)-Parâmetros!$B$9-Parâmetros!$B$10) -> 13786.923 | G6: =D6-E6-F6 -> 36053.077 | H6: =G6/C6 -> 2575.2198
A7: Cenário 4 | B7: 5000 | C7: 14 | D7: =B7*C7 -> 70000 | E7: =D7*Parâmetros!$B$4 -> 7700 | F7: =MAX(0,(MAX(0,MIN(MAX(0,D7-MAX(Parâmetros!$B$5,E7)),Escalões_IRS_2026!$C$4)-Escalões_IRS_2026!$B$4)*Escalões_IRS_2026!$D$4+MAX(0,MIN(MAX(0,D7-MAX(Parâmetros!$B$5,E7)),Escalões_IRS_2026!$C$5)-Escalões_IRS_2026!$B$5)*Escalões_IRS_2026!$D$5+MAX(0,MIN(MAX(0,D7-MAX(Parâmetros!$B$5,E7)),Escalões_IRS_2026!$C$6)-Escalões_IRS_2026!$B$6)*Escalões_IRS_2026!$D$6+MAX(0,MIN(MAX(0,D7-MAX(Parâmetros!$B$5,E7)),Escalões_IRS_2026!$C$7)-Escalões_IRS_2026!$B$7)*Escalões_IRS_2026!$D$7+MAX(0,MIN(MAX(0,D7-MAX(Parâmetros!$B$5,E7)),Escalões_IRS_2026!$C$8)-Escalões_IRS_2026!$B$8)*Escalões_IRS_2026!$D$8+MAX(0,MIN(MAX(0,D7-MAX(Parâmetros!$B$5,E7)),Escalões_IRS_2026!$C$9)-Escalões_IRS_2026!$B$9)*Escalões_IRS_2026!$D$9+MAX(0,MIN(MAX(0,D7-MAX(Parâmetros!$B$5,E7)),Escalões_IRS_2026!$C$10)-Escalões_IRS_2026!$B$10)*Escalões_IRS_2026!$D$10+MAX(0,MIN(MAX(0,D7-MAX(Parâmetros!$B$5,E7)),Escalões_IRS_2026!$C$11)-Escalões_IRS_2026!$B$11)*Escalões_IRS_2026!$D$11+MAX(0,MIN(MAX(0,D7-MAX(Parâmetros!$B$5,E7)),Escalões_IRS_2026!$C$12)-Escalões_IRS_2026!$B$12)*Escalões_IRS_2026!$D$12)-Parâmetros!$B$9-Parâmetros!$B$10) -> 19344.083 | G7: =D7-E7-F7 -> 42955.917 | H7: =G7/C7 -> 3068.2798
A8: Cenário 5 | B8: 6000 | C8: 14 | D8: =B8*C8 -> 84000 | E8: =D8*Parâmetros!$B$4 -> 9240 | F8: =MAX(0,(MAX(0,MIN(MAX(0,D8-MAX(Parâmetros!$B$5,E8)),Escalões_IRS_2026!$C$4)-Escalões_IRS_2026!$B$4)*Escalões_IRS_2026!$D$4+MAX(0,MIN(MAX(0,D8-MAX(Parâmetros!$B$5,E8)),Escalões_IRS_2026!$C$5)-Escalões_IRS_2026!$B$5)*Escalões_IRS_2026!$D$5+MAX(0,MIN(MAX(0,D8-MAX(Parâmetros!$B$5,E8)),Escalões_IRS_2026!$C$6)-Escalões_IRS_2026!$B$6)*Escalões_IRS_2026!$D$6+MAX(0,MIN(MAX(0,D8-MAX(Parâmetros!$B$5,E8)),Escalões_IRS_2026!$C$7)-Escalões_IRS_2026!$B$7)*Escalões_IRS_2026!$D$7+MAX(0,MIN(MAX(0,D8-MAX(Parâmetros!$B$5,E8)),Escalões_IRS_2026!$C$8)-Escalões_IRS_2026!$B$8)*Escalões_IRS_2026!$D$8+MAX(0,MIN(MAX(0,D8-MAX(Parâmetros!$B$5,E8)),Escalões_IRS_2026!$C$9)-Escalões_IRS_2026!$B$9)*Escalões_IRS_2026!$D$9+MAX(0,MIN(MAX(0,D8-MAX(Parâmetros!$B$5,E8)),Escalões_IRS_2026!$C$10)-Escalões_IRS_2026!$B$10)*Escalões_IRS_2026!$D$10+MAX(0,MIN(MAX(0,D8-MAX(Parâmetros!$B$5,E8)),Escalões_IRS_2026!$C$11)-Escalões_IRS_2026!$B$11)*Escalões_IRS_2026!$D$11+MAX(0,MIN(MAX(0,D8-MAX(Parâmetros!$B$5,E8)),Escalões_IRS_2026!$C$12)-Escalões_IRS_2026!$B$12)*Escalões_IRS_2026!$D$12)-Parâmetros!$B$9-Parâmetros!$B$10) -> 24901.243 | G8: =D8-E8-F8 -> 49858.757 | H8: =G8/C8 -> 3561.3398
A9: Cenário 6 | B9: 7000 | C9: 14 | D9: =B9*C9 -> 98000 | E9: =D9*Parâmetros!$B$4 -> 10780 | F9: =MAX(0,(MAX(0,MIN(MAX(0,D9-MAX(Parâmetros!$B$5,E9)),Escalões_IRS_2026!$C$4)-Escalões_IRS_2026!$B$4)*Escalões_IRS_2026!$D$4+MAX(0,MIN(MAX(0,D9-MAX(Parâmetros!$B$5,E9)),Escalões_IRS_2026!$C$5)-Escalões_IRS_2026!$B$5)*Escalões_IRS_2026!$D$5+MAX(0,MIN(MAX(0,D9-MAX(Parâmetros!$B$5,E9)),Escalões_IRS_2026!$C$6)-Escalões_IRS_2026!$B$6)*Escalões_IRS_2026!$D$6+MAX(0,MIN(MAX(0,D9-MAX(Parâmetros!$B$5,E9)),Escalões_IRS_2026!$C$7)-Escalões_IRS_2026!$B$7)*Escalões_IRS_2026!$D$7+MAX(0,MIN(MAX(0,D9-MAX(Parâmetros!$B$5,E9)),Escalões_IRS_2026!$C$8)-Escalões_IRS_2026!$B$8)*Escalões_IRS_2026!$D$8+MAX(0,MIN(MAX(0,D9-MAX(Parâmetros!$B$5,E9)),Escalões_IRS_2026!$C$9)-Escalões_IRS_2026!$B$9)*Escalões_IRS_2026!$D$9+MAX(0,MIN(MAX(0,D9-MAX(Parâmetros!$B$5,E9)),Escalões_IRS_2026!$C$10)-Escalões_IRS_2026!$B$10)*Escalões_IRS_2026!$D$10+MAX(0,MIN(MAX(0,D9-MAX(Parâmetros!$B$5,E9)),Escalões_IRS_2026!$C$11)-Escalões_IRS_2026!$B$11)*Escalões_IRS_2026!$D$11+MAX(0,MIN(MAX(0,D9-MAX(Parâmetros!$B$5,E9)),Escalões_IRS_2026!$C$12)-Escalões_IRS_2026!$B$12)*Escalões_IRS_2026!$D$12)-Parâmetros!$B$9-Parâmetros!$B$10) -> 30478.327 | G9: =D9-E9-F9 -> 56741.673 | H9: =G9/C9 -> 4052.9766

Sheet Fontes_e_Notas
A1: Fontes e Notas
A3: Tema | B3: Fonte | C3: URL | D3: Nota
A4: Retenção na fonte IRS 2026 | B4: Diário da República - Despacho n.º 233-A/2026 | C4: https://diariodarepublica.pt/dr/detalhe/despacho/233-a-2026-998488151 | D4: Tabelas de retenção para rendimentos do trabalho dependente e pensões no Continente.
A5: Tabelas de retenção IRS | B5: Portal das Finanças | C5: https://info.portaldasfinancas.gov.pt/pt/apoio_contribuinte/tabela_ret_doclib/Pages/default.aspx | D5: Consultar ficheiros oficiais de retenção atualizados.
A6: Escalões IRS 2026 | B6: Santander - Salto | C6: https://www.santander.pt/salto/escaloes-irs | D6: Usado como referência pública para escalões no modelo.
A7: Segurança Social | B7: Doutor Finanças | C7: https://www.doutorfinancas.pt/carreira-e-rendimentos/rendimentos/ja-foram-publicadas-as-tabelas-de-retencao-na-fonte-para-2026-saiba-quanto-vai-descontar/ | D7: Refere desconto de 11% para Segurança Social.
A8: Aviso | B8: Modelo estimativo | D8: O ficheiro não substitui simulação oficial de IRS nem aconselhamento fiscal.
A9: Atualização | B9: Felipe Manso | D9: Gerado em 2026-06-17.
A11: Freelancer - Segurança Social TI | B11: https://www.seg-social.pt/ptss/pssd/documento/cmc1xyfxz00dekl2ynxz676sw | C11: Rendimento relevante para prestação de serviços e contribuição TI | D11: Incluído no comparador freelancer
A12: Freelancer - IRS Cat. B Regime Simplificado | B12: https://info.portaldasfinancas.gov.pt/pt/informacao_fiscal/codigos_tributarios/cirs_rep/Pages/irs31.aspx | C12: Coeficientes do regime simplificado | D12: Incluído no comparador freelancer
A13: Freelancer - IVA Art. 53 | B13: https://info.portaldasfinancas.gov.pt/pt/informacao_fiscal/codigos_tributarios/civa_rep/Pages/artigo-53-o-do-civa.aspx | C13: Isenção de IVA no regime especial | D13: Incluído no comparador freelancer
A14: Freelancer - Dispensa de retenção | B14: https://info.portaldasfinancas.gov.pt/pt/informacao_fiscal/codigos_tributarios/cirs_rep/Pages/irs101b.aspx | C14: Dispensa de retenção em certos casos | D14: Incluído como parâmetro manual
A15: Nota de uso | B15: Validar com contabilista/AT | C15: O cálculo não substitui simulação oficial nem aconselhamento fiscal. | D15: Modelo parametrizável

Sheet Freelancer_vs_Contrato
A1: Comparador Freelancer vs Contrato - Portugal
A3: Parâmetros Freelancer | B3: Valor | C3: Nota | E3: Comparação | F3: Contrato | G3: Freelancer | H3: Diferença
A4: Taxa dia freelancer (€) | B4: 250 | C4: Valor diário sem IVA, salvo se indicar IVA incluído | E4: Bruto anual / Receita sem IVA | F4: =Simulador!B4 -> 42000 | G4: =B18 -> 60000 | H4: =G4-F4 -> 18000
A5: Dias faturáveis por mês | B5: 20 | C5: Dias médios efetivamente faturados | E5: Segurança Social anual | F5: =Simulador!B9 -> 4620 | G5: =B21 -> 8988 | H5: =G5-F5 -> 4368
A6: Meses faturáveis por ano | B6: 12 | C6: Permite considerar férias/sem projeto | E6: IRS anual estimado | F6: =Simulador!B16 -> 8835.773 | G6: =B23 -> 11651.773 | H6: =G6-F6 -> 2816
A7: Coeficiente IRS Cat. B | B7: 0.75 | C7: Regime simplificado: serviços normalmente 75% tributável | E7: Líquido anual | F7: =Simulador!B17 -> 30744.227 | G7: =B26 -> 39360.227 | H7: =G7-F7 -> 8616
A8: Rendimento relevante Segurança Social | B8: 0.7 | C8: Prestação de serviços: 70% da receita | E8: Líquido médio mensal | F8: =Simulador!B18 -> 2196.0162 | G8: =B27 -> 3280.0189 | H8: =G8-F8 -> 1084.0027
A9: Taxa Segurança Social TI | B9: 0.214 | C9: Taxa contributiva dos trabalhadores independentes | E9: Taxa efetiva | F9: =Simulador!B19 -> 0.30442925 | G9: =B28 -> 0.34399622 | H9: =G9-F9 -> 0.039566963
A10: Retenção IRS freelancer | B10: 0.25 | C10: Retenção na fonte, não é imposto final
A11: IVA | B11: 0.23 | C11: IVA normal, quando aplicável
A12: IVA incluído na taxa dia? | B12: Não | C12: Sim retira IVA da taxa; Não soma IVA à fatura
A13: Isento IVA Art. 53? | B13: Não | C13: Sim quando aplicável; limite legal depende do enquadramento
A14: Isenção SS no primeiro ano? | B14: Não | C14: Sim zera a estimativa de Segurança Social
A15: Despesas/ajustes fiscais anuais (€) | B15: 0 | C15: Campo manual para ajustes/deduções fiscais
A17: Cálculo Freelancer | B17: Valor | C17: Nota
A18: Receita anual sem IVA | B18: =IF(B12="Sim",B4*B5*B6/(1+B11),B4*B5*B6) -> 60000 | C18: Taxa dia × dias × meses; se IVA incluído, retira IVA
A19: Faturação anual com IVA | B19: =IF(B13="Sim",B18,IF(B12="Sim",B4*B5*B6,B18*(1+B11))) -> 73800 | C19: Valor cobrado ao cliente incluindo IVA quando aplicável
A20: Rendimento relevante SS | B20: =B18*B8 -> 42000 | C20: Receita sem IVA × percentual relevante
A21: Segurança Social anual TI | B21: =IF(B14="Sim",0,B20*B9) -> 8988 | C21: Rendimento relevante × taxa SS, salvo isenção
A22: Rendimento coletável Cat. B | B22: =MAX(0,B18*B7-B15) -> 45000 | C22: Receita × coeficiente - ajustes manuais
A23: IRS anual estimado | B23: =MAX(0,MIN(B22,Escalões_IRS_2026!C4)-Escalões_IRS_2026!B4)*Escalões_IRS_2026!D4+MAX(0,MIN(B22,Escalões_IRS_2026!C5)-Escalões_IRS_2026!B5)*Escalões_IRS_2026!D5+MAX(0,MIN(B22,Escalões_IRS_2026!C6)-Escalões_IRS_2026!B6)*Escalões_IRS_2026!D6+MAX(0,MIN(B22,Escalões_IRS_2026!C7)-Escalões_IRS_2026!B7)*Escalões_IRS_2026!D7+MAX(0,MIN(B22,Escalões_IRS_2026!C8)-Escalões_IRS_2026!B8)*Escalões_IRS_2026!D8+MAX(0,MIN(B22,Escalões_IRS_2026!C9)-Escalões_IRS_2026!B9)*Escalões_IRS_2026!D9+MAX(0,MIN(B22,Escalões_IRS_2026!C10)-Escalões_IRS_2026!B10)*Escalões_IRS_2026!D10+MAX(0,MIN(B22,Escalões_IRS_2026!C11)-Escalões_IRS_2026!B11)*Escalões_IRS_2026!D11+MAX(0,MIN(B22,Escalões_IRS_2026!C12)-Escalões_IRS_2026!B12)*Escalões_IRS_2026!D12 -> 11651.773 | C23: Aplicação progressiva dos escalões IRS existentes no ficheiro
A24: Retenção IRS anual | B24: =B18*B10 -> 15000 | C24: Adiantamento ao Estado, não imposto final
A25: Acerto IRS final estimado | B25: =B23-B24 -> -3348.227 | C25: IRS final - retenção já efetuada
A26: Líquido anual freelancer | B26: =B18-B21-B23 -> 39360.227 | C26: Receita sem IVA - SS - IRS final
A27: Líquido médio mensal freelancer | B27: =IFERROR(B26/B6,0) -> 3280.0189 | C27: Líquido anual / meses faturáveis
A28: Taxa efetiva freelancer | B28: =IFERROR((B21+B23)/B18,0) -> 0.34399622 | C28: (SS + IRS) / receita sem IVA
A31: Tabela rápida por taxa dia | B31: Dias/mês | C31: Meses/ano | D31: Receita anual | E31: SS anual | F31: IRS final | G31: Líquido anual | H31: Diferença vs contrato
A32: 200 | B32: =$B$5 -> 20 | C32: =$B$6 -> 12 | D32: =IF($B$12="Sim",A32*B32*C32/(1+$B$11),A32*B32*C32) -> 48000 | E32: =IF($B$14="Sim",0,(IF($B$12="Sim",A32*B32*C32/(1+$B$11),A32*B32*C32))*$B$8*$B$9) -> 7190.4 | F32: =MAX(0,MIN((MAX(0,(IF($B$12="Sim",A32*B32*C32/(1+$B$11),A32*B32*C32))*$B$7-$B$15)),Escalões_IRS_2026!C4)-Escalões_IRS_2026!B4)*Escalões_IRS_2026!D4+MAX(0,MIN((MAX(0,(IF($B$12="Sim",A32*B32*C32/(1+$B$11),A32*B32*C32))*$B$7-$B$15)),Escalões_IRS_2026!C5)-Escalões_IRS_2026!B5)*Escalões_IRS_2026!D5+MAX(0,MIN((MAX(0,(IF($B$12="Sim",A32*B32*C32/(1+$B$11),A32*B32*C32))*$B$7-$B$15)),Escalões_IRS_2026!C6)-Escalões_IRS_2026!B6)*Escalões_IRS_2026!D6+MAX(0,MIN((MAX(0,(IF($B$12="Sim",A32*B32*C32/(1+$B$11),A32*B32*C32))*$B$7-$B$15)),Escalões_IRS_2026!C7)-Escalões_IRS_2026!B7)*Escalões_IRS_2026!D7+MAX(0,MIN((MAX(0,(IF($B$12="Sim",A32*B32*C32/(1+$B$11),A32*B32*C32))*$B$7-$B$15)),Escalões_IRS_2026!C8)-Escalões_IRS_2026!B8)*Escalões_IRS_2026!D8+MAX(0,MIN((MAX(0,(IF($B$12="Sim",A32*B32*C32/(1+$B$11),A32*B32*C32))*$B$7-$B$15)),Escalões_IRS_2026!C9)-Escalões_IRS_2026!B9)*Escalões_IRS_2026!D9+MAX(0,MIN((MAX(0,(IF($B$12="Sim",A32*B32*C32/(1+$B$11),A32*B32*C32))*$B$7-$B$15)),Escalões_IRS_2026!C10)-Escalões_IRS_2026!B10)*Escalões_IRS_2026!D10+MAX(0,MIN((MAX(0,(IF($B$12="Sim",A32*B32*C32/(1+$B$11),A32*B32*C32))*$B$7-$B$15)),Escalões_IRS_2026!C11)-Escalões_IRS_2026!B11)*Escalões_IRS_2026!D11+MAX(0,MIN((MAX(0,(IF($B$12="Sim",A32*B32*C32/(1+$B$11),A32*B32*C32))*$B$7-$B$15)),Escalões_IRS_2026!C12)-Escalões_IRS_2026!B12)*Escalões_IRS_2026!D12 -> 8354.153 | G32: =D32-E32-F32 -> 32455.447 | H32: =G32-Simulador!B17 -> 1711.22
A33: 300 | B33: 18 | C33: =$B$6 -> 12 | D33: =IF($B$12="Sim",A33*B33*C33/(1+$B$11),A33*B33*C33) -> 64800 | E33: =IF($B$14="Sim",0,(IF($B$12="Sim",A33*B33*C33/(1+$B$11),A33*B33*C33))*$B$8*$B$9) -> 9707.04 | F33: =MAX(0,MIN((MAX(0,(IF($B$12="Sim",A33*B33*C33/(1+$B$11),A33*B33*C33))*$B$7-$B$15)),Escalões_IRS_2026!C4)-Escalões_IRS_2026!B4)*Escalões_IRS_2026!D4+MAX(0,MIN((MAX(0,(IF($B$12="Sim",A33*B33*C33/(1+$B$11),A33*B33*C33))*$B$7-$B$15)),Escalões_IRS_2026!C5)-Escalões_IRS_2026!B5)*Escalões_IRS_2026!D5+MAX(0,MIN((MAX(0,(IF($B$12="Sim",A33*B33*C33/(1+$B$11),A33*B33*C33))*$B$7-$B$15)),Escalões_IRS_2026!C6)-Escalões_IRS_2026!B6)*Escalões_IRS_2026!D6+MAX(0,MIN((MAX(0,(IF($B$12="Sim",A33*B33*C33/(1+$B$11),A33*B33*C33))*$B$7-$B$15)),Escalões_IRS_2026!C7)-Escalões_IRS_2026!B7)*Escalões_IRS_2026!D7+MAX(0,MIN((MAX(0,(IF($B$12="Sim",A33*B33*C33/(1+$B$11),A33*B33*C33))*$B$7-$B$15)),Escalões_IRS_2026!C8)-Escalões_IRS_2026!B8)*Escalões_IRS_2026!D8+MAX(0,MIN((MAX(0,(IF($B$12="Sim",A33*B33*C33/(1+$B$11),A33*B33*C33))*$B$7-$B$15)),Escalões_IRS_2026!C9)-Escalões_IRS_2026!B9)*Escalões_IRS_2026!D9+MAX(0,MIN((MAX(0,(IF($B$12="Sim",A33*B33*C33/(1+$B$11),A33*B33*C33))*$B$7-$B$15)),Escalões_IRS_2026!C10)-Escalões_IRS_2026!B10)*Escalões_IRS_2026!D10+MAX(0,MIN((MAX(0,(IF($B$12="Sim",A33*B33*C33/(1+$B$11),A33*B33*C33))*$B$7-$B$15)),Escalões_IRS_2026!C11)-Escalões_IRS_2026!B11)*Escalões_IRS_2026!D11+MAX(0,MIN((MAX(0,(IF($B$12="Sim",A33*B33*C33/(1+$B$11),A33*B33*C33))*$B$7-$B$15)),Escalões_IRS_2026!C12)-Escalões_IRS_2026!B12)*Escalões_IRS_2026!D12 -> 13233.883 | G33: =D33-E33-F33 -> 41859.077 | H33: =G33-Simulador!B17 -> 11114.85
A34: 260 | B34: 21 | C34: =$B$6 -> 12 | D34: =IF($B$12="Sim",A34*B34*C34/(1+$B$11),A34*B34*C34) -> 65520 | E34: =IF($B$14="Sim",0,(IF($B$12="Sim",A34*B34*C34/(1+$B$11),A34*B34*C34))*$B$8*$B$9) -> 9814.896 | F34: =MAX(0,MIN((MAX(0,(IF($B$12="Sim",A34*B34*C34/(1+$B$11),A34*B34*C34))*$B$7-$B$15)),Escalões_IRS_2026!C4)-Escalões_IRS_2026!B4)*Escalões_IRS_2026!D4+MAX(0,MIN((MAX(0,(IF($B$12="Sim",A34*B34*C34/(1+$B$11),A34*B34*C34))*$B$7-$B$15)),Escalões_IRS_2026!C5)-Escalões_IRS_2026!B5)*Escalões_IRS_2026!D5+MAX(0,MIN((MAX(0,(IF($B$12="Sim",A34*B34*C34/(1+$B$11),A34*B34*C34))*$B$7-$B$15)),Escalões_IRS_2026!C6)-Escalões_IRS_2026!B6)*Escalões_IRS_2026!D6+MAX(0,MIN((MAX(0,(IF($B$12="Sim",A34*B34*C34/(1+$B$11),A34*B34*C34))*$B$7-$B$15)),Escalões_IRS_2026!C7)-Escalões_IRS_2026!B7)*Escalões_IRS_2026!D7+MAX(0,MIN((MAX(0,(IF($B$12="Sim",A34*B34*C34/(1+$B$11),A34*B34*C34))*$B$7-$B$15)),Escalões_IRS_2026!C8)-Escalões_IRS_2026!B8)*Escalões_IRS_2026!D8+MAX(0,MIN((MAX(0,(IF($B$12="Sim",A34*B34*C34/(1+$B$11),A34*B34*C34))*$B$7-$B$15)),Escalões_IRS_2026!C9)-Escalões_IRS_2026!B9)*Escalões_IRS_2026!D9+MAX(0,MIN((MAX(0,(IF($B$12="Sim",A34*B34*C34/(1+$B$11),A34*B34*C34))*$B$7-$B$15)),Escalões_IRS_2026!C10)-Escalões_IRS_2026!B10)*Escalões_IRS_2026!D10+MAX(0,MIN((MAX(0,(IF($B$12="Sim",A34*B34*C34/(1+$B$11),A34*B34*C34))*$B$7-$B$15)),Escalões_IRS_2026!C11)-Escalões_IRS_2026!B11)*Escalões_IRS_2026!D11+MAX(0,MIN((MAX(0,(IF($B$12="Sim",A34*B34*C34/(1+$B$11),A34*B34*C34))*$B$7-$B$15)),Escalões_IRS_2026!C12)-Escalões_IRS_2026!B12)*Escalões_IRS_2026!D12 -> 13474.723 | G34: =D34-E34-F34 -> 42230.381 | H34: =G34-Simulador!B17 -> 11486.154
A35: 280 | B35: =$B$5 -> 20 | C35: =$B$6 -> 12 | D35: =IF($B$12="Sim",A35*B35*C35/(1+$B$11),A35*B35*C35) -> 67200 | E35: =IF($B$14="Sim",0,(IF($B$12="Sim",A35*B35*C35/(1+$B$11),A35*B35*C35))*$B$8*$B$9) -> 10066.56 | F35: =MAX(0,MIN((MAX(0,(IF($B$12="Sim",A35*B35*C35/(1+$B$11),A35*B35*C35))*$B$7-$B$15)),Escalões_IRS_2026!C4)-Escalões_IRS_2026!B4)*Escalões_IRS_2026!D4+MAX(0,MIN((MAX(0,(IF($B$12="Sim",A35*B35*C35/(1+$B$11),A35*B35*C35))*$B$7-$B$15)),Escalões_IRS_2026!C5)-Escalões_IRS_2026!B5)*Escalões_IRS_2026!D5+MAX(0,MIN((MAX(0,(IF($B$12="Sim",A35*B35*C35/(1+$B$11),A35*B35*C35))*$B$7-$B$15)),Escalões_IRS_2026!C6)-Escalões_IRS_2026!B6)*Escalões_IRS_2026!D6+MAX(0,MIN((MAX(0,(IF($B$12="Sim",A35*B35*C35/(1+$B$11),A35*B35*C35))*$B$7-$B$15)),Escalões_IRS_2026!C7)-Escalões_IRS_2026!B7)*Escalões_IRS_2026!D7+MAX(0,MIN((MAX(0,(IF($B$12="Sim",A35*B35*C35/(1+$B$11),A35*B35*C35))*$B$7-$B$15)),Escalões_IRS_2026!C8)-Escalões_IRS_2026!B8)*Escalões_IRS_2026!D8+MAX(0,MIN((MAX(0,(IF($B$12="Sim",A35*B35*C35/(1+$B$11),A35*B35*C35))*$B$7-$B$15)),Escalões_IRS_2026!C9)-Escalões_IRS_2026!B9)*Escalões_IRS_2026!D9+MAX(0,MIN((MAX(0,(IF($B$12="Sim",A35*B35*C35/(1+$B$11),A35*B35*C35))*$B$7-$B$15)),Escalões_IRS_2026!C10)-Escalões_IRS_2026!B10)*Escalões_IRS_2026!D10+MAX(0,MIN((MAX(0,(IF($B$12="Sim",A35*B35*C35/(1+$B$11),A35*B35*C35))*$B$7-$B$15)),Escalões_IRS_2026!C11)-Escalões_IRS_2026!B11)*Escalões_IRS_2026!D11+MAX(0,MIN((MAX(0,(IF($B$12="Sim",A35*B35*C35/(1+$B$11),A35*B35*C35))*$B$7-$B$15)),Escalões_IRS_2026!C12)-Escalões_IRS_2026!B12)*Escalões_IRS_2026!D12 -> 14036.683 | G35: =D35-E35-F35 -> 43096.757 | H35: =G35-Simulador!B17 -> 12352.53
A36: 300 | B36: =$B$5 -> 20 | C36: =$B$6 -> 12 | D36: =IF($B$12="Sim",A36*B36*C36/(1+$B$11),A36*B36*C36) -> 72000 | E36: =IF($B$14="Sim",0,(IF($B$12="Sim",A36*B36*C36/(1+$B$11),A36*B36*C36))*$B$8*$B$9) -> 10785.6 | F36: =MAX(0,MIN((MAX(0,(IF($B$12="Sim",A36*B36*C36/(1+$B$11),A36*B36*C36))*$B$7-$B$15)),Escalões_IRS_2026!C4)-Escalões_IRS_2026!B4)*Escalões_IRS_2026!D4+MAX(0,MIN((MAX(0,(IF($B$12="Sim",A36*B36*C36/(1+$B$11),A36*B36*C36))*$B$7-$B$15)),Escalões_IRS_2026!C5)-Escalões_IRS_2026!B5)*Escalões_IRS_2026!D5+MAX(0,MIN((MAX(0,(IF($B$12="Sim",A36*B36*C36/(1+$B$11),A36*B36*C36))*$B$7-$B$15)),Escalões_IRS_2026!C6)-Escalões_IRS_2026!B6)*Escalões_IRS_2026!D6+MAX(0,MIN((MAX(0,(IF($B$12="Sim",A36*B36*C36/(1+$B$11),A36*B36*C36))*$B$7-$B$15)),Escalões_IRS_2026!C7)-Escalões_IRS_2026!B7)*Escalões_IRS_2026!D7+MAX(0,MIN((MAX(0,(IF($B$12="Sim",A36*B36*C36/(1+$B$11),A36*B36*C36))*$B$7-$B$15)),Escalões_IRS_2026!C8)-Escalões_IRS_2026!B8)*Escalões_IRS_2026!D8+MAX(0,MIN((MAX(0,(IF($B$12="Sim",A36*B36*C36/(1+$B$11),A36*B36*C36))*$B$7-$B$15)),Escalões_IRS_2026!C9)-Escalões_IRS_2026!B9)*Escalões_IRS_2026!D9+MAX(0,MIN((MAX(0,(IF($B$12="Sim",A36*B36*C36/(1+$B$11),A36*B36*C36))*$B$7-$B$15)),Escalões_IRS_2026!C10)-Escalões_IRS_2026!B10)*Escalões_IRS_2026!D10+MAX(0,MIN((MAX(0,(IF($B$12="Sim",A36*B36*C36/(1+$B$11),A36*B36*C36))*$B$7-$B$15)),Escalões_IRS_2026!C11)-Escalões_IRS_2026!B11)*Escalões_IRS_2026!D11+MAX(0,MIN((MAX(0,(IF($B$12="Sim",A36*B36*C36/(1+$B$11),A36*B36*C36))*$B$7-$B$15)),Escalões_IRS_2026!C12)-Escalões_IRS_2026!B12)*Escalões_IRS_2026!D12 -> 15642.283 | G36: =D36-E36-F36 -> 45572.117 | H36: =G36-Simulador!B17 -> 14827.89
A37: 294 | B37: =$B$5 -> 20 | C37: =$B$6 -> 12 | D37: =IF($B$12="Sim",A37*B37*C37/(1+$B$11),A37*B37*C37) -> 70560 | E37: =IF($B$14="Sim",0,(IF($B$12="Sim",A37*B37*C37/(1+$B$11),A37*B37*C37))*$B$8*$B$9) -> 10569.888 | F37: =MAX(0,MIN((MAX(0,(IF($B$12="Sim",A37*B37*C37/(1+$B$11),A37*B37*C37))*$B$7-$B$15)),Escalões_IRS_2026!C4)-Escalões_IRS_2026!B4)*Escalões_IRS_2026!D4+MAX(0,MIN((MAX(0,(IF($B$12="Sim",A37*B37*C37/(1+$B$11),A37*B37*C37))*$B$7-$B$15)),Escalões_IRS_2026!C5)-Escalões_IRS_2026!B5)*Escalões_IRS_2026!D5+MAX(0,MIN((MAX(0,(IF($B$12="Sim",A37*B37*C37/(1+$B$11),A37*B37*C37))*$B$7-$B$15)),Escalões_IRS_2026!C6)-Escalões_IRS_2026!B6)*Escalões_IRS_2026!D6+MAX(0,MIN((MAX(0,(IF($B$12="Sim",A37*B37*C37/(1+$B$11),A37*B37*C37))*$B$7-$B$15)),Escalões_IRS_2026!C7)-Escalões_IRS_2026!B7)*Escalões_IRS_2026!D7+MAX(0,MIN((MAX(0,(IF($B$12="Sim",A37*B37*C37/(1+$B$11),A37*B37*C37))*$B$7-$B$15)),Escalões_IRS_2026!C8)-Escalões_IRS_2026!B8)*Escalões_IRS_2026!D8+MAX(0,MIN((MAX(0,(IF($B$12="Sim",A37*B37*C37/(1+$B$11),A37*B37*C37))*$B$7-$B$15)),Escalões_IRS_2026!C9)-Escalões_IRS_2026!B9)*Escalões_IRS_2026!D9+MAX(0,MIN((MAX(0,(IF($B$12="Sim",A37*B37*C37/(1+$B$11),A37*B37*C37))*$B$7-$B$15)),Escalões_IRS_2026!C10)-Escalões_IRS_2026!B10)*Escalões_IRS_2026!D10+MAX(0,MIN((MAX(0,(IF($B$12="Sim",A37*B37*C37/(1+$B$11),A37*B37*C37))*$B$7-$B$15)),Escalões_IRS_2026!C11)-Escalões_IRS_2026!B11)*Escalões_IRS_2026!D11+MAX(0,MIN((MAX(0,(IF($B$12="Sim",A37*B37*C37/(1+$B$11),A37*B37*C37))*$B$7-$B$15)),Escalões_IRS_2026!C12)-Escalões_IRS_2026!B12)*Escalões_IRS_2026!D12 -> 15160.603 | G37: =D37-E37-F37 -> 44829.509 | H37: =G37-Simulador!B17 -> 14085.282
A38: 650 | B38: =$B$5 -> 20 | C38: =$B$6 -> 12 | D38: =IF($B$12="Sim",A38*B38*C38/(1+$B$11),A38*B38*C38) -> 156000 | E38: =IF($B$14="Sim",0,(IF($B$12="Sim",A38*B38*C38/(1+$B$11),A38*B38*C38))*$B$8*$B$9) -> 23368.8 | F38: =MAX(0,MIN((MAX(0,(IF($B$12="Sim",A38*B38*C38/(1+$B$11),A38*B38*C38))*$B$7-$B$15)),Escalões_IRS_2026!C4)-Escalões_IRS_2026!B4)*Escalões_IRS_2026!D4+MAX(0,MIN((MAX(0,(IF($B$12="Sim",A38*B38*C38/(1+$B$11),A38*B38*C38))*$B$7-$B$15)),Escalões_IRS_2026!C5)-Escalões_IRS_2026!B5)*Escalões_IRS_2026!D5+MAX(0,MIN((MAX(0,(IF($B$12="Sim",A38*B38*C38/(1+$B$11),A38*B38*C38))*$B$7-$B$15)),Escalões_IRS_2026!C6)-Escalões_IRS_2026!B6)*Escalões_IRS_2026!D6+MAX(0,MIN((MAX(0,(IF($B$12="Sim",A38*B38*C38/(1+$B$11),A38*B38*C38))*$B$7-$B$15)),Escalões_IRS_2026!C7)-Escalões_IRS_2026!B7)*Escalões_IRS_2026!D7+MAX(0,MIN((MAX(0,(IF($B$12="Sim",A38*B38*C38/(1+$B$11),A38*B38*C38))*$B$7-$B$15)),Escalões_IRS_2026!C8)-Escalões_IRS_2026!B8)*Escalões_IRS_2026!D8+MAX(0,MIN((MAX(0,(IF($B$12="Sim",A38*B38*C38/(1+$B$11),A38*B38*C38))*$B$7-$B$15)),Escalões_IRS_2026!C9)-Escalões_IRS_2026!B9)*Escalões_IRS_2026!D9+MAX(0,MIN((MAX(0,(IF($B$12="Sim",A38*B38*C38/(1+$B$11),A38*B38*C38))*$B$7-$B$15)),Escalões_IRS_2026!C10)-Escalões_IRS_2026!B10)*Escalões_IRS_2026!D10+MAX(0,MIN((MAX(0,(IF($B$12="Sim",A38*B38*C38/(1+$B$11),A38*B38*C38))*$B$7-$B$15)),Escalões_IRS_2026!C11)-Escalões_IRS_2026!B11)*Escalões_IRS_2026!D11+MAX(0,MIN((MAX(0,(IF($B$12="Sim",A38*B38*C38/(1+$B$11),A38*B38*C38))*$B$7-$B$15)),Escalões_IRS_2026!C12)-Escalões_IRS_2026!B12)*Escalões_IRS_2026!D12 -> 44772.727 | G38: =D38-E38-F38 -> 87858.473 | H38: =G38-Simulador!B17 -> 57114.246
A39: 450 | B39: =$B$5 -> 20 | C39: =$B$6 -> 12 | D39: =IF($B$12="Sim",A39*B39*C39/(1+$B$11),A39*B39*C39) -> 108000 | E39: =IF($B$14="Sim",0,(IF($B$12="Sim",A39*B39*C39/(1+$B$11),A39*B39*C39))*$B$8*$B$9) -> 16178.4 | F39: =MAX(0,MIN((MAX(0,(IF($B$12="Sim",A39*B39*C39/(1+$B$11),A39*B39*C39))*$B$7-$B$15)),Escalões_IRS_2026!C4)-Escalões_IRS_2026!B4)*Escalões_IRS_2026!D4+MAX(0,MIN((MAX(0,(IF($B$12="Sim",A39*B39*C39/(1+$B$11),A39*B39*C39))*$B$7-$B$15)),Escalões_IRS_2026!C5)-Escalões_IRS_2026!B5)*Escalões_IRS_2026!D5+MAX(0,MIN((MAX(0,(IF($B$12="Sim",A39*B39*C39/(1+$B$11),A39*B39*C39))*$B$7-$B$15)),Escalões_IRS_2026!C6)-Escalões_IRS_2026!B6)*Escalões_IRS_2026!D6+MAX(0,MIN((MAX(0,(IF($B$12="Sim",A39*B39*C39/(1+$B$11),A39*B39*C39))*$B$7-$B$15)),Escalões_IRS_2026!C7)-Escalões_IRS_2026!B7)*Escalões_IRS_2026!D7+MAX(0,MIN((MAX(0,(IF($B$12="Sim",A39*B39*C39/(1+$B$11),A39*B39*C39))*$B$7-$B$15)),Escalões_IRS_2026!C8)-Escalões_IRS_2026!B8)*Escalões_IRS_2026!D8+MAX(0,MIN((MAX(0,(IF($B$12="Sim",A39*B39*C39/(1+$B$11),A39*B39*C39))*$B$7-$B$15)),Escalões_IRS_2026!C9)-Escalões_IRS_2026!B9)*Escalões_IRS_2026!D9+MAX(0,MIN((MAX(0,(IF($B$12="Sim",A39*B39*C39/(1+$B$11),A39*B39*C39))*$B$7-$B$15)),Escalões_IRS_2026!C10)-Escalões_IRS_2026!B10)*Escalões_IRS_2026!D10+MAX(0,MIN((MAX(0,(IF($B$12="Sim",A39*B39*C39/(1+$B$11),A39*B39*C39))*$B$7-$B$15)),Escalões_IRS_2026!C11)-Escalões_IRS_2026!B11)*Escalões_IRS_2026!D11+MAX(0,MIN((MAX(0,(IF($B$12="Sim",A39*B39*C39/(1+$B$11),A39*B39*C39))*$B$7-$B$15)),Escalões_IRS_2026!C12)-Escalões_IRS_2026!B12)*Escalões_IRS_2026!D12 -> 27684.283 | G39: =D39-E39-F39 -> 64137.317 | H39: =G39-Simulador!B17 -> 33393.09
A42: Notas importantes: o modelo de freelancer é uma estimativa para recibos verdes/regime simplificado. IVA não é rendimento; retenção é adiantamento de IRS. Valide situações específicas com contabilista/AT.
